xecution/__init__.py
xecution/common/__init__.py
xecution/common/constants.py
xecution/common/datasource_constants.py
xecution/common/enums.py
xecution/common/exchange/__init__.py
xecution/common/exchange/live_constants.py
xecution/common/exchange/testnet_constants.py
xecution/core/__init__.py
xecution/core/engine.py
xecution/models/__init__.py
xecution/models/config.py
xecution/models/order.py
xecution/models/position.py
xecution/models/topic.py
xecution/services/__init__.py
xecution/services/connection/__init__.py
xecution/services/connection/base_websockets.py
xecution/services/connection/restapi.py
xecution/services/datasource/__init__.py
xecution/services/datasource/cryptoquant.py
xecution/services/datasource/glassnode.py
xecution/services/datasource/rexilion.py
xecution/services/exchange/__init__.py
xecution/services/exchange/base_order_manager.py
xecution/services/exchange/binance_helper.py
xecution/services/exchange/binance_service.py
xecution/services/exchange/bybit_helper.py
xecution/services/exchange/bybit_service.py
xecution/services/exchange/coinbase_helper.py
xecution/services/exchange/coinbase_service.py
xecution/services/exchange/exchange_order_manager.py
xecution/services/exchange/okx_service.py
xecution/services/exchange/safe_kline_downloader.py
xecution/services/exchange/standardize.py
xecution/services/exchange/api/__init__.py
xecution/services/exchange/api/binanceapi.py
xecution/services/exchange/api/bybitapi.py
xecution/services/exchange/api/okxapi.py
xecution/services/exchange/websocket/__init__.py
xecution/services/exchange/websocket/bybitws.py
xecution/tests/__init__.py
xecution/tests/testEngine.py
xecution/utils/__init__.py
xecution/utils/logger.py
xecution/utils/utility.py
xecution-0.0.2.dist-info/METADATA
xecution-0.0.2.dist-info/WHEEL
xecution-0.0.2.dist-info/top_level.txt
xecution-0.0.2.dist-info/RECORD
