Metadata-Version: 2.4
Name: xecution
Version: 0.0.2
Summary: Trading Engine
Author: Rexilion Technologies
Author-email: fkh714@gmail.com
Requires-Python: >=3.12
Requires-Dist: numpy
Requires-Dist: aiohttp
Requires-Dist: websockets
Requires-Dist: requests
Dynamic: author
Dynamic: author-email
Dynamic: requires-dist
Dynamic: requires-python
Dynamic: summary
